autoflight
