Metadata-Version: 1.0
Name: autoflight
Version: 1.0.1
Summary: A simple script to upload a given .apk or .ipa to testflight.
Home-page: https://github.com/atooma/autoflight
Author: Andrea Stagi
Author-email: stagi.andrea@gmail.com
License: MIT
Keywords: testflight app ios android test apk ipa script
Platform: UNKNOWN
